unicontent/__init__.py
unicontent/extractors.py
unicontent/libraries.py
unicontent/paths.py
unicontent/schemas.py
unicontent/tests.py
unicontent/validators.py
unicontent-0.5.2.dist-info/DESCRIPTION.rst
unicontent-0.5.2.dist-info/METADATA
unicontent-0.5.2.dist-info/RECORD
unicontent-0.5.2.dist-info/WHEEL
unicontent-0.5.2.dist-info/metadata.json
unicontent-0.5.2.dist-info/top_level.txt
