Metadata-Version: 2.0
Name: unicontent
Version: 0.5.2
Summary: Python module to extract structured metadata from URL, DOI or ISBN
Home-page: http://github.com/hboisgibault/unicontent
Author: hboisgibault
Author-email: h.boisgibault@gmail.com
License: MIT
Keywords: metadata extraction OpenGraph DublinCore isbn GoogleBooks doi
Platform: UNKNOWN
Classifier: Development Status :: 4 - Beta
Classifier: Intended Audience :: Developers
Classifier: Topic :: Software Development :: Build Tools
Classifier: License :: OSI Approved :: MIT License
Classifier: Programming Language :: Python :: 2.7
Classifier: Programming Language :: Python :: 3
Classifier: Programming Language :: Python :: 3.2
Classifier: Programming Language :: Python :: 3.3
Classifier: Programming Language :: Python :: 3.4
Requires-Dist: bibtexparser
Requires-Dist: bs4
Requires-Dist: isbnlib
Requires-Dist: requests
Requires-Dist: tldextract
Requires-Dist: wikipedia
